ready_steady_go/__init__.py
ready_steady_go/_modidx.py
ready_steady_go/benchmark.py
ready_steady_go/cli.py
ready_steady_go-0.0.1.dist-info/LICENSE
ready_steady_go-0.0.1.dist-info/METADATA
ready_steady_go-0.0.1.dist-info/WHEEL
ready_steady_go-0.0.1.dist-info/entry_points.txt
ready_steady_go-0.0.1.dist-info/top_level.txt
ready_steady_go-0.0.1.dist-info/RECORD
