Metadata-Version: 2.1
Name: ready-steady-go
Version: 0.0.1
Summary: Synthetic Deep Learning GPU benchmark
Home-page: https://github.com/xl0/ready-steady-go
Author: Alexey Zaytsev
Author-email: alexey.zaytsev@gmail.com
License: Apache Software License 2.0
Keywords: nbdev jupyter notebook python
Classifier: Development Status :: 4 - Beta
Classifier: Intended Audience :: Developers
Classifier: Natural Language :: English
Classifier: Programming Language :: Python :: 3.8
Classifier: Programming Language :: Python :: 3.9
Classifier: Programming Language :: Python :: 3.10
Classifier: License :: OSI Approved :: Apache Software License
Requires-Python: >=3.8
License-File: LICENSE
Requires-Dist: torch
Requires-Dist: wandb
Requires-Dist: timm
Requires-Dist: tqdm
Requires-Dist: fastcore
Provides-Extra: dev
